setup.cfg
setup.py
logana/__init__.py
logana/logana.py
logana.egg-info/PKG-INFO
logana.egg-info/SOURCES.txt
logana.egg-info/dependency_links.txt
logana.egg-info/entry_points.txt
logana.egg-info/top_level.txt